autogfk/__init__.py
autogfk/admin.py
autogfk/apps.py
autogfk/fields.py
autogfk/forms.py
autogfk/managers.py
autogfk/query.py
autogfk/urls.py
autogfk/views.py
autogfk/widgets.py
autogfk/models/__init__.py
autogfk/models/base.py
autogfk/models/polymorphic.py
autogfk/static/autogfk/autogfk.css
autogfk/static/autogfk/autogfk.js
autogfk/templates/autogfk/widgets/autogfk.html
django_autogfk-0.5.2.dist-info/licenses/LICENSE
django_autogfk-0.5.2.dist-info/METADATA
django_autogfk-0.5.2.dist-info/WHEEL
django_autogfk-0.5.2.dist-info/top_level.txt
django_autogfk-0.5.2.dist-info/RECORD
