Metadata-Version: 2.4
Name: django-autogfk
Version: 0.5.2
Summary: AutoGenericForeignKey: Admin-friendly GenericForeignKey with Select2 autocomplete for Django.
Author: Sandro Salles
License: MIT
Project-URL: Homepage, https://github.com/sandro-salles/django-autogfk
Project-URL: Repository, https://github.com/sandro-salles/django-autogfk
Project-URL: Issues, https://github.com/sandro-salles/django-autogfk/issues
Keywords: django,admin,genericforeignkey,contenttypes,select2,autocomplete
Classifier: Framework :: Django
Classifier: Framework :: Django :: 4.2
Classifier: Framework :: Django :: 5.0
Classifier: Programming Language :: Python :: 3
Classifier: License :: OSI Approved :: MIT License
Classifier: Operating System :: OS Independent
Requires-Python: >=3.10
License-File: LICENSE
Requires-Dist: Django>=4.2
Provides-Extra: dev
Requires-Dist: pytest>=8.3.4; extra == "dev"
Requires-Dist: pytest-django>=4.10.0; extra == "dev"
Provides-Extra: polymorphic
Requires-Dist: django-polymorphic>=4.1.0; extra == "polymorphic"
Provides-Extra: select2
Requires-Dist: django-select2>=8.4.1; extra == "select2"
Provides-Extra: jazzmin
Requires-Dist: jazzmin>=1.14.0; extra == "jazzmin"
Dynamic: license-file
